ligotimegps/__init__.py
ligotimegps/_version.py
ligotimegps/test_ligotimegps.py
ligotimegps-2.0.1.dist-info/LICENSE
ligotimegps-2.0.1.dist-info/METADATA
ligotimegps-2.0.1.dist-info/WHEEL
ligotimegps-2.0.1.dist-info/top_level.txt
ligotimegps-2.0.1.dist-info/RECORD
