Metadata-Version: 2.1
Name: ligotimegps
Version: 2.0.1
Summary: A pure-python version of lal.LIGOTimeGPS
Home-page: https://github.com/gwpy/ligotimegps
Author: Duncan Macleod
Author-email: duncan.macleod@ligo.org
License: GPLv3
Keywords: gravitational-waves ligo lal
Platform: UNKNOWN
Classifier: Development Status :: 5 - Production/Stable
Classifier: Programming Language :: Python
Classifier: Programming Language :: Python :: 3
Classifier: Programming Language :: Python :: 3.4
Classifier: Programming Language :: Python :: 3.5
Classifier: Programming Language :: Python :: 3.6
Classifier: Programming Language :: Python :: 3.7
Classifier: Intended Audience :: Science/Research
Classifier: Natural Language :: English
Classifier: Topic :: Scientific/Engineering
Classifier: Topic :: Scientific/Engineering :: Astronomy
Classifier: Topic :: Scientific/Engineering :: Physics
Classifier: License :: OSI Approved :: GNU General Public License v3 (GPLv3)
Requires-Python: >=3.4
